{
  "version": 2,
  "limits": {
    "default_max_items": 10,
    "adjacent_reads_per_item": {"min": 2, "max": 3},
    "top_discoveries_per_research_agent": 5
  },
  "signals": {
    "prediction_market_weight": "medium",
    "prediction_market_cap": "non-dominant"
  },
  "intelligence": {
    "velocity_window_minutes": 30,
    "breaking_source_threshold": 3,
    "clustering_similarity": 0.6,
    "trend_window_minutes": 60,
    "anomaly_threshold": 2.0,
    "max_items_per_source": 3,
    "source_tiers": {
      "tier_1": ["reuters", "ap", "bbc", "guardian", "ft"],
      "tier_2": ["x", "reddit", "web"]
    }
  },
  "stages": [
    {"id": "ingress", "owner": "communication_agent", "outputs": ["request"]},
    {
      "id": "briefing",
      "owner": "orchestrator_agent",
      "inputs": ["request", "user_profile", "memory"],
      "outputs": ["weighted_brief"]
    },
    {
      "id": "research",
      "owner": "orchestrator_agent",
      "fanout": "research_agents",
      "inputs": ["weighted_brief"],
      "outputs": ["agent_reports", "agent_top5"]
    },
    {
      "id": "intelligence_enrichment",
      "owner": "orchestrator_agent",
      "inputs": ["agent_top5"],
      "outputs": ["enriched_candidates"],
      "substages": [
        "credibility_scoring",
        "cross_corroboration",
        "urgency_detection",
        "source_diversity"
      ]
    },
    {
      "id": "expert_roundtable",
      "owners": ["expert_quality_agent", "expert_relevance_agent", "expert_preference_fit_agent"],
      "inputs": ["enriched_candidates", "user_profile"],
      "outputs": ["ranked_candidates", "selected_items", "reserve_items"]
    },
    {
      "id": "narrative_threading",
      "owner": "orchestrator_agent",
      "inputs": ["selected_items"],
      "outputs": ["narrative_threads", "thread_map"]
    },
    {
      "id": "geo_risk_assessment",
      "owner": "orchestrator_agent",
      "inputs": ["enriched_candidates"],
      "outputs": ["geo_risk_index", "escalation_alerts"]
    },
    {
      "id": "trend_analysis",
      "owner": "orchestrator_agent",
      "inputs": ["enriched_candidates"],
      "outputs": ["trend_snapshots", "emerging_topics"]
    },
    {
      "id": "internal_report_drafting",
      "owner": "orchestrator_agent",
      "inputs": ["selected_items", "narrative_threads", "geo_risk_index", "trend_snapshots"],
      "outputs": ["internal_reports"]
    },
    {
      "id": "editorial_review",
      "owners": ["review_agent_style", "review_agent_clarity"],
      "inputs": ["internal_reports", "user_style_profile"],
      "outputs": ["final_user_report"]
    },
    {
      "id": "delivery",
      "owner": "communication_agent",
      "inputs": ["final_user_report"],
      "outputs": ["delivery_receipt"]
    },
    {
      "id": "feedback_writeback",
      "owner": "orchestrator_agent",
      "inputs": ["delivery_receipt", "user_feedback"],
      "outputs": ["memory_updates", "cache_updates"]
    }
  ],
  "cache_policy": {
    "key_dimensions": ["user_id", "topic_cluster", "recency_window", "confidence_band"],
    "serve_cache_before_rerun": true,
    "stale_after_minutes": 180
  }
}
